cv2/config.py
cv2/version.py
cv2/__init__.pyi
cv2/__init__.py
cv2/LICENSE-3RD-PARTY.txt
cv2/load_config_py3.py
cv2/config-3.py
cv2/py.typed
cv2/load_config_py2.py
cv2/LICENSE.txt
cv2/cv2.abi3.so
cv2/misc/version.py
cv2/misc/__init__.py
cv2/aruco/__init__.pyi
cv2/mat_wrapper/__init__.py
cv2/parallel/__init__.pyi
cv2/flann/__init__.pyi
cv2/segmentation/__init__.pyi
cv2/cuda/__init__.pyi
cv2/gapi/__init__.pyi
cv2/gapi/__init__.py
cv2/gapi/oak/__init__.pyi
cv2/gapi/video/__init__.pyi
cv2/gapi/core/__init__.pyi
cv2/gapi/core/cpu/__init__.pyi
cv2/gapi/core/fluid/__init__.pyi
cv2/gapi/core/ocl/__init__.pyi
cv2/gapi/onnx/__init__.pyi
cv2/gapi/onnx/ep/__init__.pyi
cv2/gapi/imgproc/__init__.pyi
cv2/gapi/imgproc/fluid/__init__.pyi
cv2/gapi/ov/__init__.pyi
cv2/gapi/render/__init__.pyi
cv2/gapi/render/ocv/__init__.pyi
cv2/gapi/streaming/__init__.pyi
cv2/gapi/ot/__init__.pyi
cv2/gapi/ot/cpu/__init__.pyi
cv2/gapi/own/__init__.pyi
cv2/gapi/own/detail/__init__.pyi
cv2/gapi/ie/__init__.pyi
cv2/gapi/ie/detail/__init__.pyi
cv2/gapi/wip/__init__.pyi
cv2/gapi/wip/gst/__init__.pyi
cv2/gapi/wip/onevpl/__init__.pyi
cv2/gapi/wip/draw/__init__.pyi
cv2/utils/__init__.pyi
cv2/utils/__init__.py
cv2/utils/nested/__init__.pyi
cv2/utils/fs/__init__.pyi
cv2/utils/logging/__init__.pyi
cv2/.dylibs/libtheoraenc.1.dylib
cv2/.dylibs/libsnappy.1.2.2.dylib
cv2/.dylibs/libhwy.1.2.0.dylib
cv2/.dylibs/libp11-kit.0.dylib
cv2/.dylibs/libavif.16.3.0.dylib
cv2/.dylibs/libzimg.2.dylib
cv2/.dylibs/libvmaf.3.dylib
cv2/.dylibs/libsodium.26.dylib
cv2/.dylibs/libnettle.8.10.dylib
cv2/.dylibs/libvorbisenc.2.dylib
cv2/.dylibs/libavcodec.61.19.101.dylib
cv2/.dylibs/libgnutls.30.dylib
cv2/.dylibs/librav1e.0.8.0.dylib
cv2/.dylibs/libgraphite2.3.2.1.dylib
cv2/.dylibs/libpcre2-8.0.dylib
cv2/.dylibs/libjxl_cms.0.11.1.dylib
cv2/.dylibs/libx264.164.dylib
cv2/.dylibs/libSvtAv1Enc.3.0.2.dylib
cv2/.dylibs/libtasn1.6.dylib
cv2/.dylibs/liblz4.1.10.0.dylib
opencv_python_headless-4.13.0.90.dist-info/RECORD
opencv_python_headless-4.13.0.90.dist-info/WHEEL
opencv_python_headless-4.13.0.90.dist-info/LICENSE-3RD-PARTY.txt
opencv_python_headless-4.13.0.90.dist-info/top_level.txt
opencv_python_headless-4.13.0.90.dist-info/LICENSE.txt
opencv_python_headless-4.13.0.90.dist-info/METADATA
